{"data":{"allFile":{"nodes":[{"relativePath":"content/footer/en.md","childMarkdownRemark":{"html":"","frontmatter":{"title":"En (English) footer content","content":{"left":"TOMAS VRANA","rights":"All rights reserved","info":"Information","infolink":"/information/"}}}},{"relativePath":"content/footer/cz.md","childMarkdownRemark":{"html":"","frontmatter":{"title":"En (English) footer content","content":{"left":"Tomáš Vrána","rights":"Všechna práva vyhrazena","info":"Informace","infolink":"/information/"}}}}]}}}